{"response":{"header":{"resultCode":"0000","resultMsg":"OK"},"body":{"items":{"item":[{"addr1":"인천광역시 강화군 불은면 중앙로 742-2","areacode":"2","cat1":"A02","cat2":"A0203","cat3":"A02030400","contentid":"971122","contenttypeid":"12","createdtime":"20100311105104","firstimage":"http://tong.visitkorea.or.kr/cms/resource/58/2490358_image2_1.JPG","firstimage2":"http://tong.visitkorea.or.kr/cms/resource/58/2490358_image2_1.JPG","mapx":"126.4347557746","mapy":"37.7029259337","mlevel":"6","modifiedtime":"20170417173250","readcount":"39859","sigungucode":"1","title":"강화 아르미애월드","zipcode":"23038"},{"addr1":"인천광역시 강화군 내가면 황청포구로385번길 8","areacode":"2","cat1":"A02","cat2":"A0203","cat3":"A02030100","contentid":"128385","contenttypeid":"12","createdtime":"20050419000000","firstimage":"http://tong.visitkorea.or.kr/cms/resource/15/2512715_image2_1.jpg","firstimage2":"http://tong.visitkorea.or.kr/cms/resource/15/2512715_image2_1.jpg","mapx":"126.3604121578","mapy":"37.7184755935","mlevel":"6","modifiedtime":"20180307110333","readcount":"31378","sigungucode":"1","title":"강화 용두레마을","zipcode":"23017"},{"addr1":"인천광역시 강화군 하점면 장정리","addr2":"산 122","areacode":"2","cat1":"A02","cat2":"A0201","cat3":"A02010700","contentid":"128823","contenttypeid":"12","createdtime":"20060308000000","firstimage":"http://tong.visitkorea.or.kr/cms/resource/03/183103_image2_1.jpg","firstimage2":"http://tong.visitkorea.or.kr/cms/resource/03/183103_image3_1.jpg","mapx":"126.4256099947","mapy":"37.7808861210","mlevel":"6","modifiedtime":"20180511112258","readcount":"24511","sigungucode":"1","title":"강화 장정리 석조여래입상","zipcode":"23014"},{"addr1":"인천광역시 강화군 하점면 장정리","addr2":"산 193","areacode":"2","cat1":"A02","cat2":"A0201","cat3":"A02010700","contentid":"128824","contenttypeid":"12","createdtime":"20060308000000","firstimage":"http://tong.visitkorea.or.kr/cms/resource/05/183105_image2_1.jpg","firstimage2":"http://tong.visitkorea.or.kr/cms/resource/05/183105_image3_1.jpg","mapx":"126.4203938355","mapy":"37.7798472622","mlevel":"6","modifiedtime":"20180511111725","readcount":"22606","sigungucode":"1","title":"강화 장정리 오층석탑","zipcode":"23014"},{"addr1":"인천광역시 강화군 화도면 흥왕리 산 42-1","addr2":"(화도면)","areacode":"2","cat1":"A02","cat2":"A0201","cat3":"A02010700","contentid":"127802","contenttypeid":"12","createdtime":"20040224000000","firstimage":"http://tong.visitkorea.or.kr/cms/resource/41/217641_image2_1.jpg","firstimage2":"http://tong.visitkorea.or.kr/cms/resource/41/217641_image3_1.jpg","mapx":"126.4363192460","mapy":"37.6128086877","mlevel":"6","modifiedtime":"20180511111801","readcount":"34373","sigungucode":"1","title":"강화 참성단","zipcode":"417-863"},{"addr1":"인천광역시 강화군 길상면 해안동로 58","areacode":"2","cat1":"A02","cat2":"A0201","cat3":"A02010700","contentid":"128030","contenttypeid":"12","createdtime":"20040224000000","firstimage":"http://tong.visitkorea.or.kr/cms/resource/31/688631_image2_1.jpg","firstimage2":"http://tong.visitkorea.or.kr/cms/resource/31/688631_image3_1.jpg","mapx":"126.5322543599","mapy":"37.6326163996","mlevel":"6","modifiedtime":"20170425174952","readcount":"52601","sigungucode":"1","title":"강화 초지진","zipcode":"23049"},{"addr1":"인천 강화군 강화읍 국화리","addr2":"산180번지","areacode":"2","cat1":"A02","cat2":"A0201","cat3":"A02010700","contentid":"125566","contenttypeid":"12","createdtime":"20040224000000","mapx":"126.4393070303","mapy":"37.7425658342","mlevel":"6","modifiedtime":"20180511111344","readcount":"27320","sigungucode":"1","title":"강화 홍릉","zipcode":"417-804"},{"addr1":"인천광역시 강화군 송해면 전망대로468번길 11","areacode":"2","cat1":"A02","cat2":"A0203","cat3":"A02030100","contentid":"129291","contenttypeid":"12","createdtime":"20061031000000","firstimage":"http://tong.visitkorea.or.kr/cms/resource/10/2512610_image2_1.jpg","firstimage2":"http://tong.visitkorea.or.kr/cms/resource/10/2512610_image2_1.jpg","mapx":"126.4529458372","mapy":"37.8001315783","mlevel":"3","modifiedtime":"20171025155246","readcount":"25549","sigungucode":"1","title":"강화 화문석마을","zipcode":"23013"},{"addr1":"인천광역시 강화군 화도면 해안남로","areacode":"2","cat1":"A01","cat2":"A0101","cat3":"A01010500","contentid":"1705415","contenttypeid":"12","createdtime":"20120831145548","firstimage":"http://tong.visitkorea.or.kr/cms/resource/06/643606_image2_1.jpg","firstimage2":"http://tong.visitkorea.or.kr/cms/resource/06/643606_image3_1.jpg","mapx":"126.3760356004","mapy":"37.6227842468","mlevel":"6","modifiedtime":"20180511111534","readcount":"34022","sigungucode":"1","title":"강화갯벌 및 저어새번식지","zipcode":"23061"},{"addr1":"인천광역시 강화군 강화읍 강화대로","areacode":"2","cat1":"A01","cat2":"A0101","cat3":"A01011300","contentid":"125502","contenttypeid":"12","createdtime":"20060302000000","mapx":"126.4877441465","mapy":"37.7465023392","mlevel":"6","modifiedtime":"20180427141252","readcount":"259666","sigungucode":"1","title":"강화도","zipcode":"23031"},{"addr1":"인천광역시 강화군 양사면 전망대로 797","addr2":"(양사면)","areacode":"2","cat1":"A02","cat2":"A0201","cat3":"A02011000","contentid":"631066","contenttypeid":"12","createdtime":"20081001173451","firstimage":"http://tong.visitkorea.or.kr/cms/resource/94/631194_image2_1.jpg","firstimage2":"http://tong.visitkorea.or.kr/cms/resource/94/631194_image3_1.jpg","mapx":"126.4329663820","mapy":"37.8263253898","mlevel":"6","modifiedtime":"20170913171305","readcount":"53460","sigungucode":"1","title":"강화도제적봉 평화전망대","zipcode":"23012"},{"addr1":"인천 강화군 강화읍 국화리 산3번지","addr2":", 국화리, 신문리, 관청리, 남산리","areacode":"2","cat1":"A02","cat2":"A0201","cat3":"A02010200","contentid":"125564","contenttypeid":"12","createdtime":"20060302000000","firstimage":"http://tong.visitkorea.or.kr/cms/resource/34/1579234_image2_1.jpg","firstimage2":"http://tong.visitkorea.or.kr/cms/resource/34/1579234_image3_1.jpg","mapx":"126.4838970101","mapy":"37.7560400476","mlevel":"6","modifiedtime":"20180511111254","readcount":"47114","sigungucode":"1","title":"강화산성","zipcode":"417-800"}]},"numOfRows":"12","pageNo":"24","totalCount":"9621"}}}