{"response":{"header":{"resultCode":"0000","resultMsg":"OK"},"body":{"items":{"item":[{"addr1":"전라북도 부안군 주산면 세앙길 6","addr2":"(주산면)","areacode":"37","cat1":"A02","cat2":"A0201","cat3":"A02010700","contentid":"1957009","contenttypeid":"12","createdtime":"20141016104344","mapx":"126.7034968420","mapy":"35.6666373493","mlevel":"6","modifiedtime":"20160225164120","readcount":"1263","sigungucode":"6","tel":"063-580-4386","title":"사산서원","zipcode":"56327"},{"addr1":"전라북도 임실군 관촌면","addr2":"사선6길 85","areacode":"37","cat1":"A02","cat2":"A0202","cat3":"A02020200","contentid":"126315","contenttypeid":"12","createdtime":"20031107000000","firstimage":"http://tong.visitkorea.or.kr/cms/resource/09/218809_image2_1.jpg","firstimage2":"http://tong.visitkorea.or.kr/cms/resource/09/218809_image3_1.jpg","mapx":"127.2727377727","mapy":"35.6711993836","mlevel":"3","modifiedtime":"20170426172825","readcount":"32560","sigungucode":"10","tel":"063-640-2921","title":"사선대관광지&조각공원","zipcode":"566-812"},{"addr1":"전라남도 구례군 문척면 사성암길 303","areacode":"38","cat1":"A02","cat2":"A0201","cat3":"A02010800","contentid":"2518702","contenttypeid":"12","createdtime":"20171130000052","mapx":"127.4806237813","mapy":"35.1801252038","modifiedtime":"20171228145225","readcount":"912","sigungucode":"5","tel":"사성암 061-781-4544","title":"사성암","zipcode":"57632"},{"addr1":"전라남도 구례군 문척면 사성암길 303","areacode":"38","cat1":"A02","cat2":"A0201","cat3":"A02010800","contentid":"317559","contenttypeid":"12","createdtime":"20071204140005","firstimage":"http://tong.visitkorea.or.kr/cms/resource/83/1917883_image2_1.jpg","firstimage2":"http://tong.visitkorea.or.kr/cms/resource/83/1917883_image3_1.jpg","mapx":"127.4813681800","mapy":"35.1793641909","mlevel":"6","modifiedtime":"20180201172852","readcount":"35994","sigungucode":"5","tel":"061-781-4544","title":"사성암(구례)","zipcode":"57632"},{"addr1":"경기도 안산시 단원구 와동공원로 151","addr2":"(와동)","areacode":"31","cat1":"A02","cat2":"A0201","cat3":"A02010700","contentid":"128063","contenttypeid":"12","createdtime":"20040312000000","firstimage":"http://tong.visitkorea.or.kr/cms/resource/20/2481320_image2_1.jpg","firstimage2":"http://tong.visitkorea.or.kr/cms/resource/20/2481320_image2_1.jpg","mapx":"126.8305714755","mapy":"37.3374004317","mlevel":"7","modifiedtime":"20170224171903","readcount":"18608","sigungucode":"15","title":"사세충렬문","zipcode":"15248"},{"addr1":"강원도 영월군 주천면 용석리 339","areacode":"32","cat1":"A03","cat2":"A0302","cat3":"A03021700","contentid":"2401091","contenttypeid":"12","createdtime":"20160816140145","mapx":"128.2960395564","mapy":"37.2205434946","mlevel":"6","modifiedtime":"20160913091720","readcount":"753","sigungucode":"8","tel":"010-4822-7852","title":"사슬치 캠핑장"},{"addr1":"경기도 여주시 금사면 장흥로 94","areacode":"31","cat1":"A02","cat2":"A0203","cat3":"A02030100","contentid":"128303","contenttypeid":"12","createdtime":"20050309000000","firstimage":"http://tong.visitkorea.or.kr/cms/resource/32/2481332_image2_1.jpg","firstimage2":"http://tong.visitkorea.or.kr/cms/resource/32/2481332_image2_1.jpg","mapx":"127.4734537141","mapy":"37.3754853622","mlevel":"4","modifiedtime":"20170303104949","readcount":"20678","sigungucode":"20","title":"사슴마을","zipcode":"12604"},{"addr1":"전라남도 고흥군 봉래면 사양선창길 63","areacode":"38","cat1":"A01","cat2":"A0101","cat3":"A01011300","contentid":"579169","contenttypeid":"12","createdtime":"20080624162539","firstimage":"http://tong.visitkorea.or.kr/cms/resource/62/874562_image2_1.jpg","firstimage2":"http://tong.visitkorea.or.kr/cms/resource/62/874562_image3_1.jpg","mapx":"127.4449668922","mapy":"34.4765341077","mlevel":"4","modifiedtime":"20160721144401","readcount":"20294","sigungucode":"2","title":"사양도","zipcode":"59568"},{"addr1":"경상북도 칠곡군 지천면 신동서원길 15-10","addr2":"(지천면)","areacode":"35","cat1":"A02","cat2":"A0201","cat3":"A02010700","contentid":"1958875","contenttypeid":"12","createdtime":"20141022093807","mapx":"128.4927051927","mapy":"35.9652517451","mlevel":"6","modifiedtime":"20160902214230","readcount":"1422","sigungucode":"22","title":"사양서당","zipcode":"39864"},{"addr1":"경상북도 청송군 파천면 중평병부길 50-81","areacode":"35","cat1":"A02","cat2":"A0201","cat3":"A02010700","contentid":"129119","contenttypeid":"12","createdtime":"20060703000000","firstimage":"http://tong.visitkorea.or.kr/cms/resource/46/187746_image2_1.jpg","firstimage2":"http://tong.visitkorea.or.kr/cms/resource/46/187746_image3_1.jpg","mapx":"129.0322295517","mapy":"36.4592085011","mlevel":"6","modifiedtime":"20180322163329","readcount":"17303","sigungucode":"21","title":"사양서원","zipcode":"37418"},{"addr1":"전라북도 진안군 진안읍 마이산로 228-10","areacode":"37","cat1":"A01","cat2":"A0101","cat3":"A01010500","contentid":"2519018","contenttypeid":"12","createdtime":"20171204170132","firstimage":"http://tong.visitkorea.or.kr/cms/resource/48/2521548_image2_1.JPG","firstimage2":"http://tong.visitkorea.or.kr/cms/resource/48/2521548_image2_1.JPG","mapx":"127.4119367627","mapy":"35.7681685809","mlevel":"6","modifiedtime":"20180119133013","readcount":"493","sigungucode":"14","tel":"063-430-2114","title":"사양제","zipcode":"55438"},{"addr1":"대전광역시 동구 이사로 198","addr2":"(이사동)","areacode":"3","cat1":"A02","cat2":"A0201","cat3":"A02010700","contentid":"1622907","contenttypeid":"12","createdtime":"20120504174023","firstimage":"http://tong.visitkorea.or.kr/cms/resource/65/1585565_image2_1.jpg","firstimage2":"http://tong.visitkorea.or.kr/cms/resource/65/1585565_image3_1.jpg","mapx":"127.4438813368","mapy":"36.2802024777","mlevel":"6","modifiedtime":"20160302143720","readcount":"16388","sigungucode":"2","tel":"042-271-0061","title":"사우당","zipcode":"34710"}]},"numOfRows":"12","pageNo":"321","totalCount":"9621"}}}