{"response":{"header":{"resultCode":"0000","resultMsg":"OK"},"body":{"items":{"item":[{"addr1":"대구광역시 달서구 두류공원로 200","addr2":"(두류동)","areacode":"4","cat1":"A02","cat2":"A0205","cat3":"A02050600","contentid":"1614282","contenttypeid":"12","createdtime":"20120425140711","firstimage":"http://tong.visitkorea.or.kr/cms/resource/75/1575475_image2_1.jpg","firstimage2":"http://tong.visitkorea.or.kr/cms/resource/75/1575475_image3_1.jpg","mapx":"128.5665879034","mapy":"35.8532824570","mlevel":"6","modifiedtime":"20170529143026","readcount":"31890","sigungucode":"2","title":"이월드 83타워","zipcode":"42666"},{"addr1":"충청남도 예산군 덕산면 사천리","areacode":"34","cat1":"A02","cat2":"A0201","cat3":"A02010700","contentid":"1936591","contenttypeid":"12","createdtime":"20140724100708","firstimage":"http://tong.visitkorea.or.kr/cms/resource/87/795187_image2_1.jpg","firstimage2":"http://tong.visitkorea.or.kr/cms/resource/87/795187_image3_1.jpg","mapx":"126.6218171407","mapy":"36.6611582521","mlevel":"6","modifiedtime":"20180326175314","readcount":"4376","sigungucode":"11","title":"이응로선생사적지(수덕여관)","zipcode":"32409"},{"addr1":"경기도 안산시 상록구 식물원로1길","addr2":"(일동)","areacode":"31","cat1":"A02","cat2":"A0201","cat3":"A02010700","contentid":"127195","contenttypeid":"12","createdtime":"20020510000000","firstimage":"http://tong.visitkorea.or.kr/cms/resource/11/1593511_image2_1.jpg","firstimage2":"http://tong.visitkorea.or.kr/cms/resource/11/1593511_image3_1.jpg","mapx":"126.8599999460","mapy":"37.3161700827","mlevel":"6","modifiedtime":"20180115133722","readcount":"25803","sigungucode":"15","title":"이익선생묘","zipcode":"15321"},{"addr1":"경기도 성남시 중원구 사기막골로105번길 25","addr2":"(상대원동)","areacode":"31","cat1":"A02","cat2":"A0202","cat3":"A02020400","contentid":"613372","contenttypeid":"12","createdtime":"20080821164916","mapx":"127.1735762926","mapy":"37.4402946345","mlevel":"6","modifiedtime":"20161215161201","readcount":"24479","sigungucode":"12","title":"이일천랜드","zipcode":"13201"},{"addr1":"전라북도 장수군 천천면 월곡리","addr2":"(월곡국도변)","areacode":"37","cat1":"A02","cat2":"A0201","cat3":"A02010700","contentid":"1624551","contenttypeid":"12","createdtime":"20120508092653","mapx":"127.5253120417","mapy":"35.6924041704","mlevel":"6","modifiedtime":"20160727164431","readcount":"15461","sigungucode":"11","tel":"063-350-5561, 5562","title":"이임간유허비","zipcode":"55609"},{"addr1":"광주광역시 남구 양촌길 21","addr2":"(양림동)","areacode":"5","cat1":"A02","cat2":"A0201","cat3":"A02010400","contentid":"127060","contenttypeid":"12","createdtime":"20031223000000","firstimage":"http://tong.visitkorea.or.kr/cms/resource/49/2364349_image2_1.jpg","firstimage2":"http://tong.visitkorea.or.kr/cms/resource/49/2364349_image3_1.jpg","mapx":"126.9144081354","mapy":"35.1382785681","mlevel":"6","modifiedtime":"20180528161940","readcount":"25072","sigungucode":"2","title":"이장우가옥","zipcode":"61640"},{"addr1":"서울특별시 중구 명동길 74","addr2":"(명동2가)","areacode":"1","cat1":"A02","cat2":"A0201","cat3":"A02010700","contentid":"2373363","contenttypeid":"12","createdtime":"20160317105156","firstimage":"http://tong.visitkorea.or.kr/cms/resource/94/2373194_image2_1.jpg","firstimage2":"http://tong.visitkorea.or.kr/cms/resource/94/2373194_image2_1.jpg","mapx":"126.9866120317","mapy":"37.5636019553","mlevel":"6","modifiedtime":"20160317105156","readcount":"3177","sigungucode":"24","tel":"02-2125-0848","title":"이재명 의거지","zipcode":"04537"},{"addr1":"경기도 가평군 상면 태봉골길","areacode":"31","cat1":"A02","cat2":"A0201","cat3":"A02010700","contentid":"1200953","contenttypeid":"12","createdtime":"20110210125226","mapx":"127.3310321482","mapy":"37.8012166742","mlevel":"6","modifiedtime":"20180104155631","readcount":"35289","sigungucode":"1","title":"이정구선생묘","zipcode":"12442"},{"addr1":"충청남도 태안군 원북면 옥파로 199-7","addr2":"(원북면)","areacode":"34","cat1":"A02","cat2":"A0201","cat3":"A02010500","contentid":"1532218","contenttypeid":"12","createdtime":"20120110125613","firstimage":"http://tong.visitkorea.or.kr/cms/resource/87/1954587_image2_1.jpg","firstimage2":"http://tong.visitkorea.or.kr/cms/resource/87/1954587_image3_1.jpg","mapx":"126.2400360568","mapy":"36.8316181396","mlevel":"6","modifiedtime":"20180412164614","readcount":"17530","sigungucode":"14","title":"이종일선생생가지","zipcode":"32109"},{"addr1":"강원도 정선군 임계면 수고당길 110","areacode":"32","cat1":"A02","cat2":"A0201","cat3":"A02010400","contentid":"2405846","contenttypeid":"12","createdtime":"20160829113327","mapx":"128.8483264910","mapy":"37.4847430201","mlevel":"6","modifiedtime":"20160930132037","readcount":"444","sigungucode":"11","tel":"1544-9053","title":"이종후 가옥 (동막댁 東幕宅)","zipcode":"26113"},{"addr1":"제주특별자치도 서귀포시 이중섭로 29","addr2":"(서귀동)","areacode":"39","cat1":"A02","cat2":"A0201","cat3":"A02010400","contentid":"127283","contenttypeid":"12","createdtime":"20031121000000","firstimage":"http://tong.visitkorea.or.kr/cms/resource/38/2046538_image2_1.jpg","firstimage2":"http://tong.visitkorea.or.kr/cms/resource/38/2046538_image3_1.jpg","mapx":"126.5644169991","mapy":"33.2455757555","mlevel":"6","modifiedtime":"20171024102203","readcount":"26661","sigungucode":"3","title":"이중섭 거주지","zipcode":"63595"},{"addr1":"경상남도 통영시 항남3길 25","addr2":"(항남동)","areacode":"36","cat1":"A02","cat2":"A0201","cat3":"A02010500","contentid":"584891","contenttypeid":"12","createdtime":"20080709161955","mapx":"128.4227722848","mapy":"34.8414298069","mlevel":"6","modifiedtime":"20161205151158","readcount":"25205","sigungucode":"17","title":"이중섭 거주지(통영)","zipcode":"53054"}]},"numOfRows":"12","pageNo":"564","totalCount":"9621"}}}