{"response":{"header":{"resultCode":"0000","resultMsg":"OK"},"body":{"items":{"item":[{"addr1":"서울 송파구","addr2":"잠실동, 신천동, 석촌동, 송파동, 방이동 일대","areacode":"1","cat1":"A02","cat2":"A0202","cat3":"A02020200","contentid":"1957674","contenttypeid":"12","createdtime":"20141020165245","firstimage":"http://tong.visitkorea.or.kr/cms/resource/19/722919_image2_1.jpg","firstimage2":"http://tong.visitkorea.or.kr/cms/resource/19/722919_image3_1.jpg","mapx":"127.0983644514","mapy":"37.5112350469","modifiedtime":"20170214112301","readcount":"9316","sigungucode":"18","title":"잠실 관광특구"},{"addr1":"인천광역시 중구 잠진도길 144","addr2":"(덕교동)","areacode":"2","cat1":"A01","cat2":"A0101","cat3":"A01011300","contentid":"129608","contenttypeid":"12","createdtime":"20070713000000","firstimage":"http://tong.visitkorea.or.kr/cms/resource/84/1579384_image2_1.jpg","firstimage2":"http://tong.visitkorea.or.kr/cms/resource/84/1579384_image3_1.jpg","mapx":"126.4150376954","mapy":"37.4172005232","mlevel":"6","modifiedtime":"20160628103928","readcount":"53691","sigungucode":"10","tel":"032-760-7114","title":"잠진도","zipcode":"22385"},{"addr1":"강원도 태백시 소도동 산 33-1","areacode":"32","cat1":"A01","cat2":"A0102","cat3":"A01020100","contentid":"2406367","contenttypeid":"12","createdtime":"20160830103947","mapx":"128.9432844453","mapy":"37.1242724386","mlevel":"6","modifiedtime":"20160930151406","readcount":"643","sigungucode":"14","tel":"없음","title":"잣나무 연리지"},{"addr1":"강원도 영월군 영월읍 잣봉길","addr2":"(영월읍)","areacode":"32","cat1":"A01","cat2":"A0101","cat3":"A01010400","contentid":"127300","contenttypeid":"12","createdtime":"20060509000000","firstimage":"http://tong.visitkorea.or.kr/cms/resource/19/1955719_image2_1.jpg","firstimage2":"http://tong.visitkorea.or.kr/cms/resource/19/1955719_image3_1.jpg","mapx":"128.5300732987","mapy":"37.2476614618","mlevel":"6","modifiedtime":"20170811144211","readcount":"32086","sigungucode":"8","title":"잣봉(영월)","zipcode":"26222"},{"addr1":"경기도 가평군 상면 축령로 289-146","addr2":"(상면)","areacode":"31","cat1":"A01","cat2":"A0101","cat3":"A01010500","contentid":"2407108","contenttypeid":"12","createdtime":"20160831165503","firstimage":"http://tong.visitkorea.or.kr/cms/resource/53/2405153_image2_1.jpg","firstimage2":"http://tong.visitkorea.or.kr/cms/resource/53/2405153_image3_1.jpg","mapx":"127.3365103137","mapy":"37.7707008817","mlevel":"6","modifiedtime":"20161005150629","readcount":"4739","sigungucode":"1","tel":"031-8008-6769","title":"잣향기푸른숲","zipcode":"12448"},{"addr1":"경상북도 상주시 화북면 상오3길 48","areacode":"35","cat1":"A01","cat2":"A0101","cat3":"A01010800","contentid":"126051","contenttypeid":"12","createdtime":"20040216000000","firstimage":"http://tong.visitkorea.or.kr/cms/resource/53/1891353_image2_1.jpg","firstimage2":"http://tong.visitkorea.or.kr/cms/resource/53/1891353_image3_1.jpg","mapx":"127.9202153390","mapy":"36.5268828425","mlevel":"6","modifiedtime":"20170726151832","readcount":"29556","sigungucode":"9","title":"장각폭포","zipcode":"37102"},{"addr1":"인천광역시 옹진군 영흥면 영흥로757번길 6","areacode":"2","cat1":"A01","cat2":"A0101","cat3":"A01011200","contentid":"128997","contenttypeid":"12","createdtime":"20060613000000","firstimage":"http://tong.visitkorea.or.kr/cms/resource/13/635713_image2_1.jpg","firstimage2":"http://tong.visitkorea.or.kr/cms/resource/13/635713_image3_1.jpg","mapx":"126.4499273546","mapy":"37.2726568075","mlevel":"6","modifiedtime":"20160822101438","readcount":"40253","sigungucode":"9","tel":"032-899-2114","title":"장경리해수욕장","zipcode":"23117"},{"addr1":"경기도 광주시 중부면 남한산성로 676","areacode":"31","cat1":"A02","cat2":"A0201","cat3":"A02010800","contentid":"127030","contenttypeid":"12","createdtime":"20031209000000","mapx":"127.1976119991","mapy":"37.4754382144","mlevel":"6","modifiedtime":"20170216112032","readcount":"21364","sigungucode":"5","title":"장경사(경기)","zipcode":"12700"},{"addr1":"충청남도 보령시 오천면 장고도1길","addr2":"(오천면)","areacode":"34","cat1":"A01","cat2":"A0101","cat3":"A01011300","contentid":"126819","contenttypeid":"12","createdtime":"20021203000000","mapx":"126.3381274748","mapy":"36.3966088158","mlevel":"6","modifiedtime":"20180524175041","readcount":"40479","sigungucode":"5","title":"장고도","zipcode":"33411"},{"addr1":"충청남도 청양군 대치면 장곡길 241","addr2":"(대치면)","areacode":"34","cat1":"A02","cat2":"A0201","cat3":"A02010800","contentid":"125900","contenttypeid":"12","createdtime":"20040220000000","firstimage":"http://tong.visitkorea.or.kr/cms/resource/57/1954557_image2_1.jpg","firstimage2":"http://tong.visitkorea.or.kr/cms/resource/57/1954557_image3_1.jpg","mapx":"126.8597022095","mapy":"36.4173653947","mlevel":"6","modifiedtime":"20160219105938","readcount":"7065","sigungucode":"13","tel":"041-942-6769","title":"장곡사(충남)","zipcode":"33360"},{"addr1":"인천광역시 강화군 화도면 장화리","addr2":"113","areacode":"2","cat1":"A02","cat2":"A0201","cat3":"A02010700","contentid":"1620578","contenttypeid":"12","createdtime":"20120502102257","firstimage":"http://tong.visitkorea.or.kr/cms/resource/68/1579268_image2_1.jpg","firstimage2":"http://tong.visitkorea.or.kr/cms/resource/68/1579268_image3_1.jpg","mapx":"126.3681026559","mapy":"37.6350021287","mlevel":"6","modifiedtime":"20180511112137","readcount":"16965","sigungucode":"1","title":"장곶돈대"},{"addr1":"강원도 원주시 상지대길 80","addr2":"(우산동)","areacode":"32","cat1":"A03","cat2":"A0302","cat3":"A03022700","contentid":"2396815","contenttypeid":"12","createdtime":"20160805140700","mapx":"127.9342566360","mapy":"37.3704277682","mlevel":"6","modifiedtime":"20160823175452","readcount":"313","sigungucode":"9","tel":"033-733-1330","title":"장구봉길","zipcode":"26338"}]},"numOfRows":"12","pageNo":"585","totalCount":"9621"}}}