{"response":{"header":{"resultCode":"0000","resultMsg":"OK"},"body":{"items":{"item":[{"addr1":"강원도 춘천시 북산면 추곡약수길 89-1","areacode":"32","cat1":"A01","cat2":"A0101","cat3":"A01011000","contentid":"125725","contenttypeid":"12","createdtime":"20021216000000","firstimage":"http://tong.visitkorea.or.kr/cms/resource/75/1841175_image2_1.jpg","firstimage2":"http://tong.visitkorea.or.kr/cms/resource/75/1841175_image3_1.jpg","mapx":"127.8890520721","mapy":"38.0373384358","mlevel":"6","modifiedtime":"20160803112432","readcount":"20685","sigungucode":"13","title":"추곡약수터","zipcode":"24208"},{"addr1":"강원 인제군 기린면 진동리","areacode":"32","cat1":"A01","cat2":"A0101","cat3":"A01010900","contentid":"125632","contenttypeid":"12","createdtime":"20030813000000","firstimage":"http://tong.visitkorea.or.kr/cms/resource/59/1841959_image2_1.jpg","firstimage2":"http://tong.visitkorea.or.kr/cms/resource/59/1841959_image3_1.jpg","mapx":"128.3947225226","mapy":"37.9543104878","mlevel":"6","modifiedtime":"20170818164745","readcount":"28113","sigungucode":"10","title":"추대계곡","zipcode":"252-844"},{"addr1":"경상남도 통영시 산양읍 추도리","addr2":"(산양읍)","areacode":"36","cat1":"A01","cat2":"A0101","cat3":"A01011300","contentid":"127101","contenttypeid":"12","createdtime":"20030723000000","mapx":"128.2980548247","mapy":"34.7560565760","mlevel":"6","modifiedtime":"20180523161135","readcount":"22507","sigungucode":"17","title":"추도","zipcode":"53091"},{"addr1":"대전광역시 동구 천개동로 41","addr2":"(추동)","areacode":"3","cat1":"A01","cat2":"A0101","cat3":"A01010500","contentid":"1125505","contenttypeid":"12","createdtime":"20101109110705","firstimage":"http://tong.visitkorea.or.kr/cms/resource/90/2495790_image2_1.jpg","firstimage2":"http://tong.visitkorea.or.kr/cms/resource/90/2495790_image2_1.jpg","mapx":"127.4714596636","mapy":"36.3737533832","mlevel":"6","modifiedtime":"20171101171609","readcount":"39550","sigungucode":"2","title":"추동인공생태습지","zipcode":"34500"},{"addr1":"전라북도 순창군 복흥면 석보리","areacode":"37","cat1":"A01","cat2":"A0101","cat3":"A01011800","contentid":"1612160","contenttypeid":"12","createdtime":"20120424140908","mapx":"126.9865267847","mapy":"35.4664760029","mlevel":"6","modifiedtime":"20180528160329","readcount":"16286","sigungucode":"7","title":"추령천","zipcode":"56002"},{"addr1":"경상남도 통영시 한산면","areacode":"36","cat1":"A01","cat2":"A0101","cat3":"A01011300","contentid":"127107","contenttypeid":"12","createdtime":"20040107000000","firstimage":"http://tong.visitkorea.or.kr/cms/resource/26/2027726_image2_1.jpg","firstimage2":"http://tong.visitkorea.or.kr/cms/resource/26/2027726_image3_1.jpg","mapx":"128.5210935999","mapy":"34.7617488022","mlevel":"6","modifiedtime":"20160610143750","readcount":"25078","sigungucode":"17","title":"추봉도","zipcode":"53093"},{"addr1":"충청남도 예산군 신암면 추사고택로 261","areacode":"34","cat1":"A02","cat2":"A0201","cat3":"A02010400","contentid":"125936","contenttypeid":"12","createdtime":"20020607000000","firstimage":"http://tong.visitkorea.or.kr/cms/resource/22/2357922_image2_1.jpg","firstimage2":"http://tong.visitkorea.or.kr/cms/resource/22/2357922_image3_1.jpg","mapx":"126.7998098847","mapy":"36.7468848074","mlevel":"6","modifiedtime":"20180326171323","readcount":"38455","sigungucode":"11","title":"추사고택","zipcode":"32417"},{"addr1":"충청남도 예산군 신암면 추사고택로 261","areacode":"34","cat1":"A02","cat2":"A0201","cat3":"A02010400","contentid":"1627167","contenttypeid":"12","createdtime":"20120510111850","firstimage":"http://tong.visitkorea.or.kr/cms/resource/50/2357950_image2_1.jpg","firstimage2":"http://tong.visitkorea.or.kr/cms/resource/50/2357950_image3_1.jpg","mapx":"126.7983877876","mapy":"36.7470014363","mlevel":"6","modifiedtime":"20180327103517","readcount":"19336","sigungucode":"11","title":"추사김정희선생고택·묘","zipcode":"32417"},{"addr1":"경상북도 울릉군 북면 나리","areacode":"35","cat1":"A03","cat2":"A0302","cat3":"A03022700","contentid":"2518684","contenttypeid":"12","createdtime":"20171130000009","mapx":"130.8642791005","mapy":"37.5206294377","modifiedtime":"20171228143654","readcount":"70","sigungucode":"17","tel":"문화관광체육과 054-790-6392","title":"추산 자연경관 탐방 둘레길"},{"addr1":"경상남도 창원시 마산합포구 문신길 147","addr2":"(추산동, 문신미술관) 일대","areacode":"36","cat1":"A02","cat2":"A0202","cat3":"A02020700","contentid":"2044361","contenttypeid":"12","createdtime":"20151201091720","firstimage":"http://tong.visitkorea.or.kr/cms/resource/54/2033254_image2_1.jpg","firstimage2":"http://tong.visitkorea.or.kr/cms/resource/54/2033254_image3_1.jpg","mapx":"128.5671193902","mapy":"35.2079441121","mlevel":"6","modifiedtime":"20161230150814","readcount":"3905","sigungucode":"16","tel":"055-225-3697","title":"추산근린공원","zipcode":"51281"},{"addr1":"전라북도 완주군 봉동읍 추동안길 14-7","areacode":"37","cat1":"A02","cat2":"A0201","cat3":"A02010700","contentid":"1614174","contenttypeid":"12","createdtime":"20120425133112","mapx":"127.1523325833","mapy":"35.9596811473","mlevel":"6","modifiedtime":"20180328173011","readcount":"17192","sigungucode":"8","title":"추수경장군묘역","zipcode":"55324"},{"addr1":"강원도 동해시 촛대바위길","addr2":"(추암동)","areacode":"32","cat1":"A01","cat2":"A0102","cat3":"A01020200","contentid":"129000","contenttypeid":"12","createdtime":"20060615000000","firstimage":"http://tong.visitkorea.or.kr/cms/resource/70/2001570_image2_1.jpg","firstimage2":"http://tong.visitkorea.or.kr/cms/resource/70/2001570_image3_1.jpg","mapx":"129.1604319975","mapy":"37.4795441360","mlevel":"6","modifiedtime":"20180228134833","readcount":"85850","sigungucode":"3","title":"추암 촛대바위","zipcode":"25790"}]},"numOfRows":"12","pageNo":"683","totalCount":"9621"}}}