{"response":{"header":{"resultCode":"0000","resultMsg":"OK"},"body":{"items":{"item":[{"addr1":"강원도 동해시 동해대로 6370","addr2":"(망상동)","areacode":"32","cat1":"A02","cat2":"A0203","cat3":"A02030200","contentid":"2398539","contenttypeid":"12","createdtime":"20160810094616","mapx":"129.0784245077","mapy":"37.6004313730","mlevel":"6","modifiedtime":"20170215144202","readcount":"479","sigungucode":"3","tel":"033-534-3110","title":"전통한옥","zipcode":"25700"},{"addr1":"광주광역시 서구 매월동","addr2":"513","areacode":"5","cat1":"A01","cat2":"A0101","cat3":"A01010500","contentid":"1621573","contenttypeid":"12","createdtime":"20120503142252","firstimage":"http://tong.visitkorea.or.kr/cms/resource/28/1587728_image2_1.jpg","firstimage2":"http://tong.visitkorea.or.kr/cms/resource/28/1587728_image3_1.jpg","mapx":"126.8483478833","mapy":"35.1152439432","modifiedtime":"20161103102638","readcount":"17544","sigungucode":"5","tel":"062-365-4114","title":"전평제"},{"addr1":"부산광역시 부산진구 서전로38번길","addr2":", 전포동 일대","areacode":"6","cat1":"A02","cat2":"A0203","cat3":"A02030600","contentid":"1805965","contenttypeid":"12","createdtime":"20130419111846","firstimage":"http://tong.visitkorea.or.kr/cms/resource/55/1804855_image2_1.jpg","firstimage2":"http://tong.visitkorea.or.kr/cms/resource/55/1804855_image3_1.jpg","mapx":"129.0645746453","mapy":"35.1559729295","mlevel":"6","modifiedtime":"20170510102834","readcount":"21593","sigungucode":"7","title":"전포카페거리","zipcode":"47293"},{"addr1":"경상북도 청송군 부동면 공원길 169-7","addr2":"(주왕산국립공원 내)","areacode":"35","cat1":"A01","cat2":"A0101","cat3":"A01010900","contentid":"126046","contenttypeid":"12","createdtime":"20030917000000","mapx":"128.9587483079","mapy":"37.1715950805","mlevel":"6","modifiedtime":"20180410152838","readcount":"34182","sigungucode":"21","tel":"054-873-0014~5","title":"절골계곡","zipcode":"37437"},{"addr1":"서울특별시 마포구 토정로 6","addr2":"(합정동)","areacode":"1","cat1":"A02","cat2":"A0201","cat3":"A02010900","contentid":"126528","contenttypeid":"12","createdtime":"20021101000000","firstimage":"http://tong.visitkorea.or.kr/cms/resource/80/2530780_image2_1.jpg","firstimage2":"http://tong.visitkorea.or.kr/cms/resource/80/2530780_image2_1.jpg","mapx":"126.9117221843","mapy":"37.5441500963","mlevel":"6","modifiedtime":"20180316165705","readcount":"51336","sigungucode":"13","tel":"02-3142-4434","title":"절두산 순교성지","zipcode":"04085"},{"addr1":"제주특별자치도 제주시 한경면 용수3길","areacode":"39","cat1":"A02","cat2":"A0201","cat3":"A02010700","contentid":"228864","contenttypeid":"12","createdtime":"20040226000000","firstimage":"http://tong.visitkorea.or.kr/cms/resource/90/725190_image2_1.jpg","firstimage2":"http://tong.visitkorea.or.kr/cms/resource/90/725190_image3_1.jpg","mapx":"126.1672164032","mapy":"33.3236386616","mlevel":"6","modifiedtime":"20171018143246","readcount":"19936","sigungucode":"4","title":"절부암","zipcode":"63009"},{"addr1":"부산광역시 영도구 절영로13번길 58-1","addr2":"(영선동1가)","areacode":"6","cat1":"A01","cat2":"A0101","cat3":"A01011100","contentid":"252561","contenttypeid":"12","createdtime":"20071101000000","firstimage":"http://tong.visitkorea.or.kr/cms/resource/00/1572300_image2_1.jpg","firstimage2":"http://tong.visitkorea.or.kr/cms/resource/00/1572300_image3_1.jpg","mapx":"129.0566387684","mapy":"35.0709545212","mlevel":"3","modifiedtime":"20170830145242","readcount":"36147","sigungucode":"14","title":"절영해안산책로","zipcode":"49036"},{"addr1":"제주특별자치도 서귀포시 안덕면 평화로319번길 31-11","addr2":"(안덕면)","areacode":"39","cat1":"A02","cat2":"A0203","cat3":"A02030400","contentid":"987913","contenttypeid":"12","createdtime":"20100329111913","firstimage":"http://tong.visitkorea.or.kr/cms/resource/09/1618509_image2_1.jpg","firstimage2":"http://tong.visitkorea.or.kr/cms/resource/09/1618509_image3_1.jpg","mapx":"126.3055443214","mapy":"33.2763404987","mlevel":"6","modifiedtime":"20161214142149","readcount":"25254","sigungucode":"3","title":"점보빌리지","zipcode":"63521"},{"addr1":"강원 양양군 서면","addr2":"오색리, 인제군 기린면 진동리","areacode":"32","cat1":"A01","cat2":"A0101","cat3":"A01010400","contentid":"125614","contenttypeid":"12","createdtime":"20030325000000","firstimage":"http://tong.visitkorea.or.kr/cms/resource/31/1841531_image2_1.jpg","firstimage2":"http://tong.visitkorea.or.kr/cms/resource/31/1841531_image3_1.jpg","mapx":"128.4060977411","mapy":"38.0943916451","mlevel":"6","modifiedtime":"20170830161329","readcount":"37896","sigungucode":"7","tel":"033-672-2883","title":"점봉산","zipcode":"215-810"},{"addr1":"강원도 인제군 기린면 곰배령길 12","addr2":"(기린면)","areacode":"32","cat1":"A01","cat2":"A0101","cat3":"A01010400","contentid":"572984","contenttypeid":"12","createdtime":"20080611213140","firstimage":"http://tong.visitkorea.or.kr/cms/resource/74/2005574_image2_1.jpg","firstimage2":"http://tong.visitkorea.or.kr/cms/resource/74/2005574_image3_1.jpg","mapx":"128.3751605777","mapy":"38.0393502292","mlevel":"6","modifiedtime":"20170414103241","readcount":"84247","sigungucode":"10","title":"점봉산 곰배령","zipcode":"24653"},{"addr1":"강원도 양양군","addr2":"서면 설악로 1054","areacode":"32","cat1":"A01","cat2":"A0101","cat3":"A01010400","contentid":"2353924","contenttypeid":"12","createdtime":"20151224131102","firstimage":"http://tong.visitkorea.or.kr/cms/resource/63/286263_image2_1.jpg","firstimage2":"http://tong.visitkorea.or.kr/cms/resource/63/286263_image2_1.jpg","mapx":"128.4202855055","mapy":"38.0890730928","mlevel":"6","modifiedtime":"20160104174418","readcount":"1360","sigungucode":"7","tel":"설악산국립공원사무소 033-636-7700","title":"점봉산자연산채","zipcode":"25033"},{"addr1":"전라남도 진도군 의신면 황모길 81","areacode":"38","cat1":"A01","cat2":"A0101","cat3":"A01011300","contentid":"580086","contenttypeid":"12","createdtime":"20080625171836","firstimage":"http://tong.visitkorea.or.kr/cms/resource/06/1579506_image2_1.jpg","firstimage2":"http://tong.visitkorea.or.kr/cms/resource/06/1579506_image3_1.jpg","mapx":"126.3006026790","mapy":"34.3880083832","mlevel":"6","modifiedtime":"20161215175415","readcount":"24892","sigungucode":"21","title":"접도","zipcode":"58939"}]},"numOfRows":"12","pageNo":"604","totalCount":"9621"}}}