{"response":{"header":{"resultCode":"0000","resultMsg":"OK"},"body":{"items":{"item":[{"addr1":"전라남도 화순군 도곡면 고인돌1로","addr2":"일대","areacode":"38","cat1":"A02","cat2":"A0201","cat3":"A02010700","contentid":"127190","contenttypeid":"12","createdtime":"20020612000000","mapx":"126.9178560502","mapy":"34.9869568050","mlevel":"6","modifiedtime":"20171130135651","readcount":"34073","sigungucode":"24","title":"화순 고인돌군 유적 [유네스코 세계문화유산]","zipcode":"58154"},{"addr1":"제주특별자치도 서귀포시 안덕면 화순해안로","addr2":"(화순리)","areacode":"39","cat1":"A01","cat2":"A0101","cat3":"A01011200","contentid":"126443","contenttypeid":"12","createdtime":"20030925000000","firstimage":"http://tong.visitkorea.or.kr/cms/resource/38/197738_image2_1.jpg","firstimage2":"http://tong.visitkorea.or.kr/cms/resource/38/197738_image3_1.jpg","mapx":"126.3335149080","mapy":"33.2407004292","mlevel":"6","modifiedtime":"20171024113356","readcount":"39524","sigungucode":"3","title":"화순 금모래 해변","zipcode":"63530"},{"addr1":"전남 화순군 북면 송단리","addr2":"송단마을","areacode":"38","cat1":"A02","cat2":"A0201","cat3":"A02010600","contentid":"127034","contenttypeid":"12","createdtime":"20020506000000","firstimage":"http://tong.visitkorea.or.kr/cms/resource/97/2515997_image2_1.jpg","firstimage2":"http://tong.visitkorea.or.kr/cms/resource/97/2515997_image2_1.jpg","mapx":"127.1570881864","mapy":"35.1894019218","mlevel":"6","modifiedtime":"20171130140337","readcount":"28824","sigungucode":"24","title":"화순 복조리마을","zipcode":"519-923"},{"addr1":"전라남도 화순군 북면 백아로 2080","areacode":"38","cat1":"A01","cat2":"A0101","cat3":"A01010500","contentid":"127191","contenttypeid":"12","createdtime":"20031114000000","firstimage":"http://tong.visitkorea.or.kr/cms/resource/23/1608223_image2_1.jpg","firstimage2":"http://tong.visitkorea.or.kr/cms/resource/23/1608223_image3_1.jpg","mapx":"127.0906362225","mapy":"35.1695863575","mlevel":"6","modifiedtime":"20171026160724","readcount":"27591","sigungucode":"24","title":"화순 서유리 공룡발자국화석 산지","zipcode":"58100"},{"addr1":"전라남도 화순군 화순읍 만수길 42","areacode":"38","cat1":"A02","cat2":"A0203","cat3":"A02030100","contentid":"129368","contenttypeid":"12","createdtime":"20061113000000","mapx":"127.0078343746","mapy":"35.0920159254","mlevel":"6","modifiedtime":"20171130141629","readcount":"25536","sigungucode":"24","tel":"061-373-2193","title":"화순 수만리들국화마을","zipcode":"58104"},{"addr1":"전라남도 화순군 이양면 쌍산의로 459","areacode":"38","cat1":"A02","cat2":"A0201","cat3":"A02010700","contentid":"250389","contenttypeid":"12","createdtime":"20071025000000","mapx":"127.0606598252","mapy":"34.8876259521","mlevel":"6","modifiedtime":"20160902214140","readcount":"17308","sigungucode":"24","title":"화순 쌍봉사 철감선사탑","zipcode":"58165"},{"addr1":"전라남도 화순군 이서면 야사은행나무길 7","addr2":"(이서면)","areacode":"38","cat1":"A01","cat2":"A0102","cat3":"A01020100","contentid":"128984","contenttypeid":"12","createdtime":"20060529000000","firstimage":"http://tong.visitkorea.or.kr/cms/resource/76/186776_image2_1.jpg","firstimage2":"http://tong.visitkorea.or.kr/cms/resource/76/186776_image2_1.jpg","mapx":"127.0778610558","mapy":"35.1107899966","mlevel":"6","modifiedtime":"20171026163603","readcount":"21804","sigungucode":"24","title":"화순 야사리 은행나무","zipcode":"58103"},{"addr1":"전라남도 화순군 동복면 독상1길 48-1","areacode":"38","cat1":"A02","cat2":"A0201","cat3":"A02010500","contentid":"742566","contenttypeid":"12","createdtime":"20090527142539","firstimage":"http://tong.visitkorea.or.kr/cms/resource/56/742256_image2_1.jpg","firstimage2":"http://tong.visitkorea.or.kr/cms/resource/56/742256_image3_1.jpg","mapx":"127.1303463628","mapy":"35.0691566945","mlevel":"6","modifiedtime":"20160902214717","readcount":"16785","sigungucode":"24","title":"화순 오지호 생가","zipcode":"58102"},{"addr1":"전라남도 화순군 능주면 정암길 32","areacode":"38","cat1":"A02","cat2":"A0201","cat3":"A02010700","contentid":"127189","contenttypeid":"12","createdtime":"20020513000000","mapx":"126.9535083063","mapy":"34.9931567073","mlevel":"6","modifiedtime":"20170109171816","readcount":"20287","sigungucode":"24","title":"화순 정암 조광조선생 적려 유허비","zipcode":"58153"},{"addr1":"전라남도 화순군 화순읍 지강로","areacode":"38","cat1":"A02","cat2":"A0201","cat3":"A02010700","contentid":"742654","contenttypeid":"12","createdtime":"20090527145210","firstimage":"http://tong.visitkorea.or.kr/cms/resource/27/742027_image2_1.jpg","firstimage2":"http://tong.visitkorea.or.kr/cms/resource/27/742027_image3_1.jpg","mapx":"126.8996447114","mapy":"35.0606731877","mlevel":"6","modifiedtime":"20180124161456","readcount":"16980","sigungucode":"24","title":"화순광산이씨승지공비","zipcode":"58108"},{"addr1":"전라남도 화순군 능주면 학포로","areacode":"38","cat1":"A02","cat2":"A0201","cat3":"A02010700","contentid":"127349","contenttypeid":"12","createdtime":"20040227000000","firstimage":"http://tong.visitkorea.or.kr/cms/resource/75/742075_image2_1.jpg","firstimage2":"http://tong.visitkorea.or.kr/cms/resource/75/742075_image3_1.jpg","mapx":"126.9631189626","mapy":"34.9773642040","mlevel":"6","modifiedtime":"20171026170004","readcount":"17377","sigungucode":"24","title":"화순능주삼충각","zipcode":"58153"},{"addr1":"전라남도 화순군 화순읍 학포로","addr2":"(대리)","areacode":"38","cat1":"A02","cat2":"A0201","cat3":"A02010700","contentid":"231903","contenttypeid":"12","createdtime":"20071005000000","mapx":"126.9705831371","mapy":"35.0508921544","mlevel":"6","modifiedtime":"20171026164458","readcount":"20641","sigungucode":"24","title":"화순대리석불입상","zipcode":"58149"}]},"numOfRows":"12","pageNo":"778","totalCount":"9621"}}}