{"response":{"header":{"resultCode":"0000","resultMsg":"OK"},"body":{"items":{"item":[{"addr1":"부산광역시 영도구 태종로 729","addr2":"(동삼동)","areacode":"6","cat1":"A02","cat2":"A0206","cat3":"A02060300","contentid":"130774","contenttypeid":"14","createdtime":"20060327000000","firstimage":"http://tong.visitkorea.or.kr/cms/resource/48/1572248_image2_1.jpg","firstimage2":"http://tong.visitkorea.or.kr/cms/resource/48/1572248_image3_1.jpg","mapx":"129.0796423170","mapy":"35.0712160269","mlevel":"6","modifiedtime":"20180528105317","readcount":"27389","sigungucode":"14","title":"동삼동패총전시관","zipcode":"49125"},{"addr1":"서울특별시 종로구 동숭길 122","addr2":"(동숭동)","areacode":"1","cat1":"A02","cat2":"A0206","cat3":"A02060600","contentid":"130700","contenttypeid":"14","createdtime":"20051222000000","firstimage":"http://tong.visitkorea.or.kr/cms/resource/99/668099_image2_1.jpg","firstimage2":"http://tong.visitkorea.or.kr/cms/resource/99/668099_image3_1.jpg","mapx":"127.0037015708","mapy":"37.5837027034","mlevel":"6","modifiedtime":"20180518100800","readcount":"18339","sigungucode":"23","title":"동숭아트센터","zipcode":"03084"},{"addr1":"전라남도 나주시 건재로 185","addr2":"(대호동)","areacode":"38","cat1":"A02","cat2":"A0206","cat3":"A02060100","contentid":"130917","contenttypeid":"14","createdtime":"20070710000000","firstimage":"http://tong.visitkorea.or.kr/cms/resource/45/217145_image2_1.jpg","firstimage2":"http://tong.visitkorea.or.kr/cms/resource/45/217145_image3_1.jpg","mapx":"126.7185276274","mapy":"35.0507990391","mlevel":"6","modifiedtime":"20180312112335","readcount":"20223","sigungucode":"6","title":"동신대 카메라박물관(문화박물관)","zipcode":"58245"},{"addr1":"부산광역시 서구 구덕로 225","addr2":"(부민동2가)","areacode":"6","cat1":"A02","cat2":"A0206","cat3":"A02060100","contentid":"130521","contenttypeid":"14","createdtime":"20041007000000","mapx":"129.0187911335","mapy":"35.1049250231","mlevel":"6","modifiedtime":"20170724175516","readcount":"19498","sigungucode":"11","title":"동아대학교 박물관","zipcode":"49236"},{"addr1":"부산광역시 서구 대신공원로 32","addr2":"(동대신동3가)","areacode":"6","cat1":"A02","cat2":"A0206","cat3":"A02060600","contentid":"1608524","contenttypeid":"14","createdtime":"20120420100324","mapx":"129.0187462610","mapy":"35.1207704706","mlevel":"6","modifiedtime":"20170804144458","readcount":"16855","sigungucode":"11","title":"동아대학교 석당홀","zipcode":"49201"},{"addr1":"강원도 강릉시 죽헌길 140-12","addr2":"(죽헌동)","areacode":"32","cat1":"A02","cat2":"A0206","cat3":"A02060100","contentid":"1318353","contenttypeid":"14","createdtime":"20110628112650","firstimage":"http://tong.visitkorea.or.kr/cms/resource/06/2363006_image2_1.jpg","firstimage2":"http://tong.visitkorea.or.kr/cms/resource/06/2363006_image3_1.jpg","mapx":"128.8803035030","mapy":"37.7779681022","mlevel":"6","modifiedtime":"20180116140509","readcount":"48413","sigungucode":"1","title":"동양자수박물관","zipcode":"25465"},{"addr1":"대구광역시 중구 봉산문화길 42","addr2":"(봉산동)","areacode":"4","cat1":"A02","cat2":"A0206","cat3":"A02060500","contentid":"129932","contenttypeid":"14","createdtime":"20071106013603","firstimage":"http://tong.visitkorea.or.kr/cms/resource/45/1888845_image2_1.jpg","firstimage2":"http://tong.visitkorea.or.kr/cms/resource/45/1888845_image3_1.jpg","mapx":"128.5981626570","mapy":"35.8620126066","mlevel":"6","modifiedtime":"20180315170653","readcount":"37005","sigungucode":"8","title":"동원화랑","zipcode":"41959"},{"addr1":"부산광역시 부산진구 엄광로 176","addr2":"(가야동)","areacode":"6","cat1":"A02","cat2":"A0206","cat3":"A02060900","contentid":"130345","contenttypeid":"14","createdtime":"20071106015322","firstimage":"http://tong.visitkorea.or.kr/cms/resource/22/1982322_image2_1.jpg","firstimage2":"http://tong.visitkorea.or.kr/cms/resource/22/1982322_image3_1.jpg","mapx":"129.0346331923","mapy":"35.1418461812","mlevel":"6","modifiedtime":"20171026160130","readcount":"27016","sigungucode":"7","title":"동의대학교 중앙도서관","zipcode":"47340"},{"addr1":"서울특별시 동작구 장승배기로 94","addr2":"(노량진동)","areacode":"1","cat1":"A02","cat2":"A0206","cat3":"A02060900","contentid":"130770","contenttypeid":"14","createdtime":"20060320000000","firstimage":"http://tong.visitkorea.or.kr/cms/resource/32/1895032_image2_1.jpg","firstimage2":"http://tong.visitkorea.or.kr/cms/resource/32/1895032_image3_1.jpg","mapx":"126.9405206377","mapy":"37.5059328296","mlevel":"6","modifiedtime":"20180206174049","readcount":"22316","sigungucode":"12","title":"동작도서관","zipcode":"06925"},{"addr1":"서울특별시 동작구 장승배기로10길 42","addr2":"(상도동)","areacode":"1","cat1":"A02","cat2":"A0206","cat3":"A02060700","contentid":"130247","contenttypeid":"14","createdtime":"20071106014844","firstimage":"http://tong.visitkorea.or.kr/cms/resource/48/1894748_image2_1.jpg","firstimage2":"http://tong.visitkorea.or.kr/cms/resource/48/1894748_image3_1.jpg","mapx":"126.9409873013","mapy":"37.5045385555","mlevel":"6","modifiedtime":"20180123171021","readcount":"22144","sigungucode":"12","title":"동작문화원","zipcode":"06963"},{"addr1":"전라남도 구례군 구례읍 동편제길 53","areacode":"38","cat1":"A02","cat2":"A0206","cat3":"A02061100","contentid":"130558","contenttypeid":"14","createdtime":"20050408000000","firstimage":"http://tong.visitkorea.or.kr/cms/resource/19/643919_image2_1.jpg","firstimage2":"http://tong.visitkorea.or.kr/cms/resource/19/643919_image3_1.jpg","mapx":"127.4581248447","mapy":"35.2158568958","mlevel":"6","modifiedtime":"20180124145229","readcount":"23698","sigungucode":"5","title":"동편제 판소리전수관","zipcode":"57647"},{"addr1":"전라북도 정읍시 덕천면 동학로 742","areacode":"37","cat1":"A02","cat2":"A0206","cat3":"A02060200","contentid":"775041","contenttypeid":"14","createdtime":"20090804102910","firstimage":"http://tong.visitkorea.or.kr/cms/resource/20/197120_image2_1.jpg","firstimage2":"http://tong.visitkorea.or.kr/cms/resource/20/197120_image3_1.jpg","mapx":"126.8283254782","mapy":"35.6328516450","mlevel":"6","modifiedtime":"20171013135233","readcount":"25590","sigungucode":"13","title":"동학농민혁명기념관","zipcode":"56149"}]},"numOfRows":"12","pageNo":"42","totalCount":"1695"}}}