{"response":{"header":{"resultCode":"0000","resultMsg":"OK"},"body":{"items":{"item":[{"addr1":"경기도 용인시 처인구 원삼면 두창호수로 105","areacode":"31","cat1":"A02","cat2":"A0207","cat3":"A02070200","contentid":"2525596","contenttypeid":"15","createdtime":"20171226154942","firstimage":"http://tong.visitkorea.or.kr/cms/resource/77/2525577_image2_1.jpg","firstimage2":"http://tong.visitkorea.or.kr/cms/resource/77/2525577_image2_1.jpg","mapx":"127.3343838462","mapy":"37.1488451580","mlevel":"6","modifiedtime":"20180111175321","readcount":"3770","sigungucode":"23","tel":"031-339-3696","title":"용인빙어축제 2018","zipcode":"17176"},{"addr1":"경기도 용인시 처인구 중부대로 1199","addr2":"(삼가동)","areacode":"31","cat1":"A02","cat2":"A0207","cat3":"A02070200","contentid":"2431706","contenttypeid":"15","createdtime":"20161004174836","firstimage":"http://tong.visitkorea.or.kr/cms/resource/89/2508289_image2_1.jpg","firstimage2":"http://tong.visitkorea.or.kr/cms/resource/89/2508289_image2_1.jpg","mapx":"127.1774732269","mapy":"37.2412455395","mlevel":"6","modifiedtime":"20170921161903","readcount":"4409","sigungucode":"23","tel":"031-324-2083","title":"용인사이버과학축제 2017","zipcode":"17019"},{"addr1":"경기도 용인시 처인구 포곡읍 에버랜드로562번길 38","areacode":"31","cat1":"A02","cat2":"A0207","cat3":"A02070200","contentid":"1802741","contenttypeid":"15","createdtime":"20130402164231","firstimage":"http://tong.visitkorea.or.kr/cms/resource/55/2488855_image2_1.JPG","firstimage2":"http://tong.visitkorea.or.kr/cms/resource/55/2488855_image2_1.JPG","mapx":"127.1916898843","mapy":"37.2944674134","mlevel":"6","modifiedtime":"20180328145453","readcount":"91170","sigungucode":"23","tel":"용인 에버랜드 031-320-5000","title":"용인에버 벚꽃축제 2018","zipcode":"17021"},{"addr1":"충청북도 충주시 관아1길 28","addr2":"(성내동)","areacode":"33","cat1":"A02","cat2":"A0207","cat3":"A02070200","contentid":"1358165","contenttypeid":"15","createdtime":"20110810143346","firstimage":"http://tong.visitkorea.or.kr/cms/resource/52/2509852_image2_1.jpg","firstimage2":"http://tong.visitkorea.or.kr/cms/resource/52/2509852_image2_1.jpg","mapx":"127.9364013477","mapy":"36.9700878518","mlevel":"6","modifiedtime":"20171011144543","readcount":"28020","sigungucode":"11","tel":"043-847-1565","title":"우륵문화제 2017","zipcode":"27388"},{"addr1":"경기도 남양주시 진접읍 해밀예당1로 96","areacode":"31","cat1":"A02","cat2":"A0207","cat3":"A02070200","contentid":"2491444","contenttypeid":"15","createdtime":"20170428101547","firstimage":"http://tong.visitkorea.or.kr/cms/resource/52/2544152_image2_1.png","firstimage2":"http://tong.visitkorea.or.kr/cms/resource/52/2544152_image2_1.png","mapx":"127.1910140196","mapy":"37.7170016987","mlevel":"6","modifiedtime":"20180424175043","readcount":"2033","sigungucode":"9","tel":"031-560-1562~3","title":"우아한 비상 2018","zipcode":"12057"},{"addr1":"대전광역시 동구 충정로 53","addr2":"(가양동)","areacode":"3","cat1":"A02","cat2":"A0207","cat3":"A02070200","contentid":"1851201","contenttypeid":"15","createdtime":"20131015092111","firstimage":"http://tong.visitkorea.or.kr/cms/resource/43/1092543_image2_1.jpg","firstimage2":"http://tong.visitkorea.or.kr/cms/resource/43/1092543_image3_1.jpg","mapx":"127.4584420365","mapy":"36.3497420088","mlevel":"6","modifiedtime":"20171019141756","readcount":"6404","sigungucode":"2","tel":"042-251-4205","title":"우암문화제 2017","zipcode":"34505"},{"addr1":"경기도 고양시 일산동구 장항동 845","areacode":"31","cat1":"A02","cat2":"A0207","cat3":"A02070200","contentid":"2383986","contenttypeid":"15","createdtime":"20160516142823","firstimage":"http://tong.visitkorea.or.kr/cms/resource/85/2383985_image2_1.JPG","firstimage2":"http://tong.visitkorea.or.kr/cms/resource/85/2383985_image2_1.JPG","mapx":"126.8704933173","mapy":"37.5190078377","mlevel":"6","modifiedtime":"20180523103740","readcount":"5579","sigungucode":"2","tel":"02-588-7202~3","title":"우유의 날&국내산 치즈 페스티벌 2018","zipcode":"10409"},{"addr1":"경남 창녕군 창녕읍 말흘리","areacode":"36","cat1":"A02","cat2":"A0207","cat3":"A02070200","contentid":"1117084","contenttypeid":"15","createdtime":"20101026151016","firstimage":"http://tong.visitkorea.or.kr/cms/resource/54/1853354_image2_1.JPG","firstimage2":"http://tong.visitkorea.or.kr/cms/resource/54/1853354_image2_1.JPG","mapx":"128.5512623599","mapy":"35.5185255471","mlevel":"6","modifiedtime":"20171017104830","readcount":"20415","sigungucode":"15","tel":"055-530-6122~4","title":"우포누리축제 2017","zipcode":"635-800"},{"addr1":"경상남도 창녕군 유어면 우포늪길 220","addr2":"(유어면)","areacode":"36","cat1":"A02","cat2":"A0207","cat3":"A02070200","contentid":"1752170","contenttypeid":"15","createdtime":"20121114160606","firstimage":"http://tong.visitkorea.or.kr/cms/resource/07/2037607_image2_1.JPG","firstimage2":"http://tong.visitkorea.or.kr/cms/resource/07/2037607_image2_1.JPG","mapx":"128.4184566432","mapy":"35.5445840791","mlevel":"6","modifiedtime":"20171206162908","readcount":"18018","sigungucode":"15","tel":"055-530-1525","title":"우포늪 생명길 걷기대회 2017","zipcode":"50304"},{"addr1":"경기 포천시 화현면","addr2":"화현리","areacode":"31","cat1":"A02","cat2":"A0207","cat3":"A02070200","contentid":"1398114","contenttypeid":"15","createdtime":"20111007174853","firstimage":"http://tong.visitkorea.or.kr/cms/resource/99/1187399_image2_1.jpg","firstimage2":"http://tong.visitkorea.or.kr/cms/resource/99/1187399_image3_1.jpg","mapx":"127.3231361610","mapy":"37.8789019281","mlevel":"6","modifiedtime":"20170921175156","readcount":"24299","sigungucode":"29","tel":"화현면사무소 031-538-4702","title":"운악산단풍축제 2017","zipcode":"487-840"},{"addr1":"경상북도 울릉군 울릉읍 저동리 48-11","areacode":"35","cat1":"A02","cat2":"A0207","cat3":"A02070200","contentid":"766923","contenttypeid":"15","createdtime":"20090715165025","mapx":"130.9079787879","mapy":"37.4972441380","mlevel":"6","modifiedtime":"20170711164729","readcount":"33539","sigungucode":"17","tel":"054-790-6391, 6425","title":"울릉도 오징어축제 2017","zipcode":"799-804"},{"addr1":"울산광역시 울주군 서생면 간절곶1길 39-2","addr2":"(서생면)","areacode":"7","cat1":"A02","cat2":"A0207","cat3":"A02070200","contentid":"141375","contenttypeid":"15","createdtime":"20061219000000","firstimage":"http://tong.visitkorea.or.kr/cms/resource/68/2028368_image2_1.jpg","firstimage2":"http://tong.visitkorea.or.kr/cms/resource/68/2028368_image2_1.jpg","mapx":"129.3605738299","mapy":"35.3589668021","mlevel":"6","modifiedtime":"20171108132827","readcount":"39710","sigungucode":"5","tel":"052-229-7633","title":"울산 간절곶 해맞이축제 2018","zipcode":"45015"}]},"numOfRows":"12","pageNo":"92","totalCount":"1774"}}}