{"response":{"header":{"resultCode":"0000","resultMsg":"OK"},"body":{"items":{"item":[{"addr1":"경상북도 구미시 해평면 해평4길 12","addr2":"(해평면)","areacode":"35","cat1":"A03","cat2":"A0302","cat3":"A03020200","contentid":"131208","contenttypeid":"28","createdtime":"20030120000000","firstimage":"http://tong.visitkorea.or.kr/cms/resource/71/1893671_image2_1.jpg","firstimage2":"http://tong.visitkorea.or.kr/cms/resource/71/1893671_image3_1.jpg","mapx":"128.3702845280","mapy":"36.1975758827","mlevel":"6","modifiedtime":"20180118095528","readcount":"26436","sigungucode":"4","tel":"054-474-0912","title":"구미시청소년수련원","zipcode":"39154"},{"addr1":"경상북도 구미시 산호대로 243","addr2":"(공단동)","areacode":"35","cat1":"A03","cat2":"A0302","cat3":"A03020200","contentid":"131207","contenttypeid":"28","createdtime":"20020723000000","firstimage":"http://tong.visitkorea.or.kr/cms/resource/65/1893665_image2_1.jpg","firstimage2":"http://tong.visitkorea.or.kr/cms/resource/65/1893665_image3_1.jpg","mapx":"128.3839303392","mapy":"36.1055477077","mlevel":"6","modifiedtime":"20180111091638","readcount":"21651","sigungucode":"4","tel":"054-480-4300","title":"구미시평생교육원","zipcode":"39371"},{"addr1":"경상남도 통영시 한산면 매죽리","addr2":"(한산면)","areacode":"36","cat1":"A03","cat2":"A0303","cat3":"A03030600","contentid":"131629","contenttypeid":"28","createdtime":"20020710000000","mapx":"128.5493792431","mapy":"34.5796057333","mlevel":"6","modifiedtime":"20180409164332","readcount":"18552","sigungucode":"17","tel":"055-650-4553","title":"구을비도","zipcode":"53097"},{"addr1":"전라북도 무주군 설천면 구천동로 1101","addr2":"(설천면)","areacode":"37","cat1":"A03","cat2":"A0302","cat3":"A03022600","contentid":"510546","contenttypeid":"28","createdtime":"20080312161025","firstimage":"http://tong.visitkorea.or.kr/cms/resource/55/446655_image2_1.jpg","firstimage2":"http://tong.visitkorea.or.kr/cms/resource/55/446655_image3_1.jpg","mapx":"127.7592799068","mapy":"35.9111307052","mlevel":"6","modifiedtime":"20171205151856","readcount":"13737","sigungucode":"5","tel":"063-322-6655","title":"국가대표","zipcode":"55555"},{"addr1":"경상남도 통영시 욕지면 중촌길","addr2":"(욕지면)","areacode":"36","cat1":"A03","cat2":"A0303","cat3":"A03030600","contentid":"131626","contenttypeid":"28","createdtime":"20020710000000","mapx":"128.4422534258","mapy":"34.5411331127","mlevel":"6","modifiedtime":"20180413104023","readcount":"19239","sigungucode":"17","tel":"055-650-4553","title":"국도","zipcode":"53100"},{"addr1":"충청남도 천안시 동남구 목천읍 서리4길 48","addr2":"(목천읍)","areacode":"34","cat1":"A03","cat2":"A0302","cat3":"A03020200","contentid":"131847","contenttypeid":"28","createdtime":"20070904000000","firstimage":"http://tong.visitkorea.or.kr/cms/resource/85/1876085_image2_1.jpg","firstimage2":"http://tong.visitkorea.or.kr/cms/resource/85/1876085_image3_1.jpg","mapx":"127.2287479169","mapy":"36.7862767300","mlevel":"6","modifiedtime":"20180124140215","readcount":"22702","sigungucode":"12","tel":"041-620-7700","title":"국립중앙청소년수련원","zipcode":"31229"},{"addr1":"강원도 평창군 용평면 새터마을길 108","addr2":"(용평면)","areacode":"32","cat1":"A03","cat2":"A0302","cat3":"A03020200","contentid":"131633","contenttypeid":"28","createdtime":"20060125000000","firstimage":"http://tong.visitkorea.or.kr/cms/resource/55/1583655_image2_1.jpg","firstimage2":"http://tong.visitkorea.or.kr/cms/resource/55/1583655_image3_1.jpg","mapx":"128.4019747918","mapy":"37.5832203033","mlevel":"6","modifiedtime":"20180124102926","readcount":"16815","sigungucode":"15","tel":"033-330-0800","title":"국립평창청소년수련원","zipcode":"25316"},{"addr1":"경상북도 경주시 산내면 문복로 1280-7","addr2":"(산내면)","areacode":"35","cat1":"A03","cat2":"A0302","cat3":"A03020200","contentid":"131460","contenttypeid":"28","createdtime":"20020729000000","mapx":"129.0625474253","mapy":"35.7424347490","mlevel":"6","modifiedtime":"20180103103737","readcount":"21013","sigungucode":"2","tel":"054-751-4300","title":"국민청소년수련원","zipcode":"38187"},{"addr1":"인천광역시 강화군 강화읍 국화길 51","addr2":"(강화읍)","areacode":"2","cat1":"A03","cat2":"A0303","cat3":"A03030500","contentid":"1615657","contenttypeid":"28","createdtime":"20120426103109","firstimage":"http://tong.visitkorea.or.kr/cms/resource/61/1575661_image2_1.jpg","firstimage2":"http://tong.visitkorea.or.kr/cms/resource/61/1575661_image3_1.jpg","mapx":"126.4680459296","mapy":"37.7473074541","mlevel":"6","modifiedtime":"20170810141245","readcount":"16134","sigungucode":"1","tel":"010-3448-6783","title":"국화지낚시터","zipcode":"23028"},{"addr1":"전라북도 군산시 옥서면 남군산로 1685","addr2":"(옥서면)","areacode":"37","cat1":"A03","cat2":"A0302","cat3":"A03020700","contentid":"776717","contenttypeid":"28","createdtime":"20090811094858","mapx":"126.6539010233","mapy":"35.8933412412","mlevel":"6","modifiedtime":"20171208091703","readcount":"28163","sigungucode":"2","tel":"063-472-3355","title":"군산컨트리클럽","zipcode":"54170"},{"addr1":"강원도 철원군 갈말읍 직탕길 26","addr2":"(갈말읍)","areacode":"32","cat1":"A03","cat2":"A0305","cat3":"A03050100","contentid":"1971302","contenttypeid":"28","createdtime":"20141205155450","firstimage":"http://tong.visitkorea.or.kr/cms/resource/45/1947645_image2_1.jpg","firstimage2":"http://tong.visitkorea.or.kr/cms/resource/45/1947645_image3_1.jpg","mapx":"127.2705979818","mapy":"38.2073876191","mlevel":"6","modifiedtime":"20170712131916","readcount":"1703","sigungucode":"12","tel":"033-452-1253","title":"굿레저","zipcode":"24028"},{"addr1":"서울특별시 광진구 워커힐로 177","addr2":"(광장동)","areacode":"1","cat1":"A03","cat2":"A0303","cat3":"A03030700","contentid":"131610","contenttypeid":"28","createdtime":"20020711000000","mapx":"127.1116924462","mapy":"37.5586325612","mlevel":"6","modifiedtime":"20170929143149","readcount":"121752","sigungucode":"6","tel":"02-450-4607","title":"그랜드 워커힐 리버파크(야외수영장)","zipcode":"04963"}]},"numOfRows":"12","pageNo":"11","totalCount":"1403"}}}