{"response":{"header":{"resultCode":"0000","resultMsg":"OK"},"body":{"items":{"item":[{"addr1":"경상남도 산청군 산청읍 산수로 316-6","areacode":"36","cat1":"A05","cat2":"A0502","cat3":"A05020100","contentid":"1019687","contenttypeid":"39","createdtime":"20100512135217","firstimage":"http://tong.visitkorea.or.kr/cms/resource/17/1023117_image2_1.jpg","firstimage2":"http://tong.visitkorea.or.kr/cms/resource/17/1023117_image3_1.jpg","mapx":"127.8652274969","mapy":"35.4427023185","mlevel":"6","modifiedtime":"20171129171109","readcount":"20167","sigungucode":"9","tel":"055-972-2988","title":"송림산장","zipcode":"52212"},{"addr1":"서울특별시 광진구 자양번영로 79","addr2":"(자양동)","areacode":"1","cat1":"A05","cat2":"A0502","cat3":"A05020100","contentid":"2373384","contenttypeid":"39","createdtime":"20160317143707","firstimage":"http://tong.visitkorea.or.kr/cms/resource/70/2372570_image2_1.jpg","firstimage2":"http://tong.visitkorea.or.kr/cms/resource/70/2372570_image3_1.jpg","mapx":"127.0764712775","mapy":"37.5366761431","mlevel":"6","modifiedtime":"20170228110232","readcount":"4241","sigungucode":"6","tel":"02-457-5473","title":"송림식당","zipcode":"05066"},{"addr1":"충청북도 진천군 이월면 진안로 362-6","addr2":"(이월면)","areacode":"33","cat1":"A05","cat2":"A0502","cat3":"A05020100","contentid":"134521","contenttypeid":"39","createdtime":"20040119000000","firstimage":"http://tong.visitkorea.or.kr/cms/resource/48/1849848_image2_1.jpg","firstimage2":"http://tong.visitkorea.or.kr/cms/resource/48/1849848_image3_1.jpg","mapx":"127.3996862838","mapy":"36.9509108360","mlevel":"6","modifiedtime":"20180124144221","readcount":"17886","sigungucode":"8","tel":"043-536-2233","title":"송백가든","zipcode":"27812"},{"addr1":"충청북도 진천군 초평면 초평로 1051-5","addr2":"(초평면)","areacode":"33","cat1":"A05","cat2":"A0502","cat3":"A05020100","contentid":"133375","contenttypeid":"39","createdtime":"20031010000000","firstimage":"http://tong.visitkorea.or.kr/cms/resource/76/1850876_image2_1.jpg","firstimage2":"http://tong.visitkorea.or.kr/cms/resource/76/1850876_image3_1.jpg","mapx":"127.5178100489","mapy":"36.8134065703","mlevel":"6","modifiedtime":"20180302102316","readcount":"18329","sigungucode":"8","tel":"043-532-6228","title":"송애집","zipcode":"27859"},{"addr1":"경상남도 합천군 대병면 합천호수로 13-3","addr2":"(대병면)","areacode":"36","cat1":"A05","cat2":"A0502","cat3":"A05020100","contentid":"1916554","contenttypeid":"39","createdtime":"20140428094754","mapx":"128.0202145468","mapy":"35.5206546051","mlevel":"6","modifiedtime":"20171012101934","readcount":"2344","sigungucode":"21","tel":"055-931-6816","title":"송옥가든","zipcode":"50216"},{"addr1":"인천광역시 남구 미추홀대로719번길 28","addr2":"(주안동)","areacode":"2","cat1":"A05","cat2":"A0502","cat3":"A05020100","contentid":"135743","contenttypeid":"39","createdtime":"20070503000000","firstimage":"http://tong.visitkorea.or.kr/cms/resource/69/1884569_image2_1.jpg","firstimage2":"http://tong.visitkorea.or.kr/cms/resource/69/1884569_image3_1.jpg","mapx":"126.6785457469","mapy":"37.4619166192","mlevel":"6","modifiedtime":"20170818142535","readcount":"17013","sigungucode":"3","tel":"032-872-2000, 032-874-5252","title":"송원","zipcode":"22136"},{"addr1":"서울특별시 중구 동호로24길 15","addr2":"(장충동2가)","areacode":"1","cat1":"A05","cat2":"A0502","cat3":"A05020100","contentid":"133836","contenttypeid":"39","createdtime":"20031001000000","firstimage":"http://tong.visitkorea.or.kr/cms/resource/28/1871928_image2_1.jpg","firstimage2":"http://tong.visitkorea.or.kr/cms/resource/28/1871928_image3_1.jpg","mapx":"127.0051243384","mapy":"37.5599054951","mlevel":"6","modifiedtime":"20171024153403","readcount":"17331","sigungucode":"24","tel":"02-2275-3118","title":"송원","zipcode":"04617"},{"addr1":"서울특별시 중구 남대문로5길 39","addr2":"(소공동)","areacode":"1","cat1":"A05","cat2":"A0502","cat3":"A05020300","contentid":"133809","contenttypeid":"39","createdtime":"20031230000000","firstimage":"http://tong.visitkorea.or.kr/cms/resource/79/1813779_image2_1.jpg","firstimage2":"http://tong.visitkorea.or.kr/cms/resource/79/1813779_image3_1.jpg","mapx":"126.9785711103","mapy":"37.5631518636","mlevel":"6","modifiedtime":"20170627154539","readcount":"27148","sigungucode":"24","tel":"02-755-3979","title":"송원복집","zipcode":"04526"},{"addr1":"인천광역시 남동구 문화서로4번길 61-14","addr2":"(구월3동)","areacode":"2","cat1":"A05","cat2":"A0502","cat3":"A05020100","contentid":"404049","contenttypeid":"39","createdtime":"20080119222852","firstimage":"http://tong.visitkorea.or.kr/cms/resource/69/401269_image2_1.jpg","firstimage2":"http://tong.visitkorea.or.kr/cms/resource/69/401269_image3_1.jpg","mapx":"126.6985499439","mapy":"37.4451855829","mlevel":"6","modifiedtime":"20171130150307","readcount":"17933","sigungucode":"4","tel":"032-432-6948","title":"송원식당","zipcode":"21568"},{"addr1":"강원도 평창군 봉평면 태기로 481","addr2":"(봉평면)","areacode":"32","cat1":"A05","cat2":"A0502","cat3":"A05020100","contentid":"135485","contenttypeid":"39","createdtime":"20061215000000","firstimage":"http://tong.visitkorea.or.kr/cms/resource/85/448285_image2_1.jpg","firstimage2":"http://tong.visitkorea.or.kr/cms/resource/85/448285_image3_1.jpg","mapx":"128.3489829352","mapy":"37.5637326604","mlevel":"6","modifiedtime":"20180207105158","readcount":"16980","sigungucode":"15","tel":"033-333-4096","title":"송원해장국","zipcode":"25309"},{"addr1":"경기도 동두천시 큰시장로 28-10","addr2":"(생연동)","areacode":"31","cat1":"A05","cat2":"A0502","cat3":"A05020100","contentid":"133450","contenttypeid":"39","createdtime":"20030829000000","firstimage":"http://tong.visitkorea.or.kr/cms/resource/81/1022281_image2_1.jpg","firstimage2":"http://tong.visitkorea.or.kr/cms/resource/81/1022281_image3_1.jpg","mapx":"127.0549294811","mapy":"37.9008528115","mlevel":"6","modifiedtime":"20161005110559","readcount":"33869","sigungucode":"10","tel":"031-865-2428, 862-6606","title":"송월관","zipcode":"11333"},{"addr1":"경상북도 청송군 부동면 주왕산로 504","addr2":"(부동면)","areacode":"35","cat1":"A05","cat2":"A0502","cat3":"A05020100","contentid":"134653","contenttypeid":"39","createdtime":"20040922000000","firstimage":"http://tong.visitkorea.or.kr/cms/resource/80/1981680_image2_1.jpg","firstimage2":"http://tong.visitkorea.or.kr/cms/resource/80/1981680_image3_1.jpg","mapx":"129.1106360701","mapy":"36.3789996737","mlevel":"6","modifiedtime":"20170807142057","readcount":"20662","sigungucode":"21","tel":"054-874-0066","title":"송이가든","zipcode":"37437"}]},"numOfRows":"12","pageNo":"203","totalCount":"4932"}}}